Workbook

Sheet database_monthly
A1: year | B1: month | C1: mdate | D1: usdidr | E1: trade_bal_usdbn | F1: net_flows_idrtn | G1: fx_reserves_usdbn | H1: dxy | I1: ust10y_pct | J1: vix | K1: bi_rate_pct | L1: ff_lower_pct | M1: ff_upper_pct | N1: ff_mid_pct | O1: bi_ff_diff_pp | P1: rating_up | Q1: rating_down | R1: outlook_up | S1: outlook_down | T1: exports_usdbn | U1: imports_usdbn | V1: bi_framework7d | W1: srbi_exists | X1: baseline_sample | Y1: core_complete
A2: 2013 | B2: 1 | C2: =12*(A2-1960)+B2-1 -> 636 | D2: 9740 | E2: =IF(COUNT(T2:U2)=2,T2-U2,"") -> -0.0745 | F2: =IF(COUNT(flow_components!C2:E2)=3,SUM(flow_components!C2:E2),"") -> 7.6655523 | G2: 101.18941 | H2: 79.207 | I2: 1.9849 | J2: 14.28 | K2: 5.75 | L2: 0 | M2: 0.25 | N2: =(L2+M2)/2 -> 0.125 | O2: =K2-N2 -> 5.625 | P2: =IF(COUNTIFS(rating_events!$B$2:$B$13,C2,rating_events!$D$2:$D$13,"rating_upgrade")>0,1,0) -> 0 | Q2: =IF(COUNTIFS(rating_events!$B$2:$B$13,C2,rating_events!$D$2:$D$13,"rating_downgrade")>0,1,0) -> 0 | R2: =IF(COUNTIFS(rating_events!$B$2:$B$13,C2,rating_events!$D$2:$D$13,"outlook_improvement")>0,1,0) -> 0 | S2: =IF(COUNTIFS(rating_events!$B$2:$B$13,C2,rating_events!$D$2:$D$13,"outlook_deterioration")>0,1,0) -> 0 | T2: 15.3755 | U2: 15.45 | V2: 0 | W2: 0 | X2: =IF(AND(A2>=2014,Y2=1),1,0) -> 0 | Y2: =IF(COUNT(D2:H2)=5,1,0) -> 1
A3: 2013 | B3: 2 | C3: =12*(A3-1960)+B3-1 -> 637 | D3: 9664 | E3: =IF(COUNT(T3:U3)=2,T3-U3,"") -> -0.2974 | F3: =IF(COUNT(flow_components!C3:E3)=3,SUM(flow_components!C3:E3),"") -> 18.402592 | G3: 97.82412 | H3: 81.949 | I3: 1.8756 | J3: 15.51 | K3: 5.75 | L3: 0 | M3: 0.25 | N3: =(L3+M3)/2 -> 0.125 | O3: =K3-N3 -> 5.625 | P3: =IF(COUNTIFS(rating_events!$B$2:$B$13,C3,rating_events!$D$2:$D$13,"rating_upgrade")>0,1,0) -> 0 | Q3: =IF(COUNTIFS(rating_events!$B$2:$B$13,C3,rating_events!$D$2:$D$13,"rating_downgrade")>0,1,0) -> 0 | R3: =IF(COUNTIFS(rating_events!$B$2:$B$13,C3,rating_events!$D$2:$D$13,"outlook_improvement")>0,1,0) -> 0 | S3: =IF(COUNTIFS(rating_events!$B$2:$B$13,C3,rating_events!$D$2:$D$13,"outlook_deterioration")>0,1,0) -> 0 | T3: 15.0156 | U3: 15.313 | V3: 0 | W3: 0 | X3: =IF(AND(A3>=2014,Y3=1),1,0) -> 0 | Y3: =IF(COUNT(D3:H3)=5,1,0) -> 1
A4: 2013 | B4: 3 | C4: =12*(A4-1960)+B4-1 -> 638 | D4: 9715 | E4: =IF(COUNT(T4:U4)=2,T4-U4,"") -> 0.1376 | F4: =IF(COUNT(flow_components!C4:E4)=3,SUM(flow_components!C4:E4),"") -> 0.538039 | G4: 97.47481 | H4: 82.976 | I4: 1.8486 | J4: 12.7 | K4: 5.75 | L4: 0 | M4: 0.25 | N4: =(L4+M4)/2 -> 0.125 | O4: =K4-N4 -> 5.625 | P4: =IF(COUNTIFS(rating_events!$B$2:$B$13,C4,rating_events!$D$2:$D$13,"rating_upgrade")>0,1,0) -> 0 | Q4: =IF(COUNTIFS(rating_events!$B$2:$B$13,C4,rating_events!$D$2:$D$13,"rating_downgrade")>0,1,0) -> 0 | R4: =IF(COUNTIFS(rating_events!$B$2:$B$13,C4,rating_events!$D$2:$D$13,"outlook_improvement")>0,1,0) -> 0 | S4: =IF(COUNTIFS(rating_events!$B$2:$B$13,C4,rating_events!$D$2:$D$13,"outlook_deterioration")>0,1,0) -> 0 | T4: 15.0246 | U4: 14.887 | V4: 0 | W4: 0 | X4: =IF(AND(A4>=2014,Y4=1),1,0) -> 0 | Y4: =IF(COUNT(D4:H4)=5,1,0) -> 1
A5: 2013 | B5: 4 | C5: =12*(A5-1960)+B5-1 -> 639 | D5: 9723 | E5: =IF(COUNT(T5:U5)=2,T5-U5,"") -> -1.7021 | F5: =IF(COUNT(flow_components!C5:E5)=3,SUM(flow_components!C5:E5),"") -> 16.462113 | G5: 100.19661 | H5: 81.746 | I5: 1.6717 | J5: 13.52 | K5: 5.75 | L5: 0 | M5: 0.25 | N5: =(L5+M5)/2 -> 0.125 | O5: =K5-N5 -> 5.625 | P5: =IF(COUNTIFS(rating_events!$B$2:$B$13,C5,rating_events!$D$2:$D$13,"rating_upgrade")>0,1,0) -> 0 | Q5: =IF(COUNTIFS(rating_events!$B$2:$B$13,C5,rating_events!$D$2:$D$13,"rating_downgrade")>0,1,0) -> 0 | R5: =IF(COUNTIFS(rating_events!$B$2:$B$13,C5,rating_events!$D$2:$D$13,"outlook_improvement")>0,1,0) -> 0 | S5: =IF(COUNTIFS(rating_events!$B$2:$B$13,C5,rating_events!$D$2:$D$13,"outlook_deterioration")>0,1,0) -> 0 | T5: 14.7609 | U5: 16.463 | V5: 0 | W5: 0 | X5: =IF(AND(A5>=2014,Y5=1),1,0) -> 0 | Y5: =IF(COUNT(D5:H5)=5,1,0) -> 1
A6: 2013 | B6: 5 | C6: =12*(A6-1960)+B6-1 -> 640 | D6: 9795 | E6: =IF(COUNT(T6:U6)=2,T6-U6,"") -> -0.5276 | F6: =IF(COUNT(flow_components!C6:E6)=3,SUM(flow_components!C6:E6),"") -> 3.5941488 | G6: 98.2008 | H6: 83.375 | I6: 2.1282 | J6: 16.3 | K6: 5.75 | L6: 0 | M6: 0.25 | N6: =(L6+M6)/2 -> 0.125 | O6: =K6-N6 -> 5.625 | P6: =IF(COUNTIFS(rating_events!$B$2:$B$13,C6,rating_events!$D$2:$D$13,"rating_upgrade")>0,1,0) -> 0 | Q6: =IF(COUNTIFS(rating_events!$B$2:$B$13,C6,rating_events!$D$2:$D$13,"rating_downgrade")>0,1,0) -> 0 | R6: =IF(COUNTIFS(rating_events!$B$2:$B$13,C6,rating_events!$D$2:$D$13,"outlook_improvement")>0,1,0) -> 0 | S6: =IF(COUNTIFS(rating_events!$B$2:$B$13,C6,rating_events!$D$2:$D$13,"outlook_deterioration")>0,1,0) -> 1 | T6: 16.1334 | U6: 16.661 | V6: 0 | W6: 0 | X6: =IF(AND(A6>=2014,Y6=1),1,0) -> 0 | Y6: =IF(COUNT(D6:H6)=5,1,0) -> 1
A7: 2013 | B7: 6 | C7: =12*(A7-1960)+B7-1 -> 641 | D7: 9925 | E7: =IF(COUNT(T7:U7)=2,T7-U7,"") -> -0.8772 | F7: =IF(COUNT(flow_components!C7:E7)=3,SUM(flow_components!C7:E7),"") -> -39.392305 | G7: 91.57255 | H7: 83.136 | I7: 2.4857 | J7: 16.86 | K7: 6 | L7: 0 | M7: 0.25 | N7: =(L7+M7)/2 -> 0.125 | O7: =K7-N7 -> 5.875 | P7: =IF(COUNTIFS(rating_events!$B$2:$B$13,C7,rating_events!$D$2:$D$13,"rating_upgrade")>0,1,0) -> 0 | Q7: =IF(COUNTIFS(rating_events!$B$2:$B$13,C7,rating_events!$D$2:$D$13,"rating_downgrade")>0,1,0) -> 0 | R7: =IF(COUNTIFS(rating_events!$B$2:$B$13,C7,rating_events!$D$2:$D$13,"outlook_improvement")>0,1,0) -> 0 | S7: =IF(COUNTIFS(rating_events!$B$2:$B$13,C7,rating_events!$D$2:$D$13,"outlook_deterioration")>0,1,0) -> 0 | T7: 14.7588 | U7: 15.636 | V7: 0 | W7: 0 | X7: =IF(AND(A7>=2014,Y7=1),1,0) -> 0 | Y7: =IF(COUNT(D7:H7)=5,1,0) -> 1
A8: 2013 | B8: 7 | C8: =12*(A8-1960)+B8-1 -> 642 | D8: 10278 | E8: =IF(COUNT(T8:U8)=2,T8-U8,"") -> -2.3291 | F8: =IF(COUNT(flow_components!C8:E8)=3,SUM(flow_components!C8:E8),"") -> 0.32980407 | G8: 85.91298 | H8: 81.452 | I8: 2.5762 | J8: 13.45 | K8: 6.5 | L8: 0 | M8: 0.25 | N8: =(L8+M8)/2 -> 0.125 | O8: =K8-N8 -> 6.375 | P8: =IF(COUNTIFS(rating_events!$B$2:$B$13,C8,rating_events!$D$2:$D$13,"rating_upgrade")>0,1,0) -> 0 | Q8: =IF(COUNTIFS(rating_events!$B$2:$B$13,C8,rating_events!$D$2:$D$13,"rating_downgrade")>0,1,0) -> 0 | R8: =IF(COUNTIFS(rating_events!$B$2:$B$13,C8,rating_events!$D$2:$D$13,"outlook_improvement")>0,1,0) -> 0 | S8: =IF(COUNTIFS(rating_events!$B$2:$B$13,C8,rating_events!$D$2:$D$13,"outlook_deterioration")>0,1,0) -> 0 | T8: 15.0879 | U8: 17.417 | V8: 0 | W8: 0 | X8: =IF(AND(A8>=2014,Y8=1),1,0) -> 0 | Y8: =IF(COUNT(D8:H8)=5,1,0) -> 1
A9: 2013 | B9: 8 | C9: =12*(A9-1960)+B9-1 -> 643 | D9: 10920 | E9: =IF(COUNT(T9:U9)=2,T9-U9,"") -> 0.0717 | F9: =IF(COUNT(flow_components!C9:E9)=3,SUM(flow_components!C9:E9),"") -> -7.8353427 | G9: 86.02947 | H9: 82.087 | I9: 2.7839 | J9: 17.01 | K9: 7 | L9: 0 | M9: 0.25 | N9: =(L9+M9)/2 -> 0.125 | O9: =K9-N9 -> 6.875 | P9: =IF(COUNTIFS(rating_events!$B$2:$B$13,C9,rating_events!$D$2:$D$13,"rating_upgrade")>0,1,0) -> 0 | Q9: =IF(COUNTIFS(rating_events!$B$2:$B$13,C9,rating_events!$D$2:$D$13,"rating_downgrade")>0,1,0) -> 0 | R9: =IF(COUNTIFS(rating_events!$B$2:$B$13,C9,rating_events!$D$2:$D$13,"outlook_improvement")>0,1,0) -> 0 | S9: =IF(COUNTIFS(rating_events!$B$2:$B$13,C9,rating_events!$D$2:$D$13,"outlook_deterioration")>0,1,0) -> 0 | T9: 13.0837 | U9: 13.012 | V9: 0 | W9: 0 | X9: =IF(AND(A9>=2014,Y9=1),1,0) -> 0 | Y9: =IF(COUNT(D9:H9)=5,1,0) -> 1
A10: 2013 | B10: 9 | C10: =12*(A10-1960)+B10-1 -> 644 | D10: 11580 | E10: =IF(COUNT(T10:U10)=2,T10-U10,"") -> -0.8032 | F10: =IF(COUNT(flow_components!C10:E10)=3,SUM(flow_components!C10:E10),"") -> 9.7647999 | G10: 88.85079 | H10: 80.221 | I10: 2.61 | J10: 16.6 | K10: 7.25 | L10: 0 | M10: 0.25 | N10: =(L10+M10)/2 -> 0.125 | O10: =K10-N10 -> 7.125 | P10: =IF(COUNTIFS(rating_events!$B$2:$B$13,C10,rating_events!$D$2:$D$13,"rating_upgrade")>0,1,0) -> 0 | Q10: =IF(COUNTIFS(rating_events!$B$2:$B$13,C10,rating_events!$D$2:$D$13,"rating_downgrade")>0,1,0) -> 0 | R10: =IF(COUNTIFS(rating_events!$B$2:$B$13,C10,rating_events!$D$2:$D$13,"outlook_improvement")>0,1,0) -> 0 | S10: =IF(COUNTIFS(rating_events!$B$2:$B$13,C10,rating_events!$D$2:$D$13,"outlook_deterioration")>0,1,0) -> 0 | T10: 14.7068 | U10: 15.51 | V10: 0 | W10: 0 | X10: =IF(AND(A10>=2014,Y10=1),1,0) -> 0 | Y10: =IF(COUNT(D10:H10)=5,1,0) -> 1
A11: 2013 | B11: 10 | C11: =12*(A11-1960)+B11-1 -> 645 | D11: 11273 | E11: =IF(COUNT(T11:U11)=2,T11-U11,"") -> 0.0243 | F11: =IF(COUNT(flow_components!C11:E11)=3,SUM(flow_components!C11:E11),"") -> 21.169082 | G11: 90.108424 | H11: 80.195 | I11: 2.5542 | J11: 13.75 | K11: 7.25 | L11: 0 | M11: 0.25 | N11: =(L11+M11)/2 -> 0.125 | O11: =K11-N11 -> 7.125 | P11: =IF(COUNTIFS(rating_events!$B$2:$B$13,C11,rating_events!$D$2:$D$13,"rating_upgrade")>0,1,0) -> 0 | Q11: =IF(COUNTIFS(rating_events!$B$2:$B$13,C11,rating_events!$D$2:$D$13,"rating_downgrade")>0,1,0) -> 0 | R11: =IF(COUNTIFS(rating_events!$B$2:$B$13,C11,rating_events!$D$2:$D$13,"outlook_improvement")>0,1,0) -> 0 | S11: =IF(COUNTIFS(rating_events!$B$2:$B$13,C11,rating_events!$D$2:$D$13,"outlook_deterioration")>0,1,0) -> 0 | T11: 15.6983 | U11: 15.674 | V11: 0 | W11: 0 | X11: =IF(AND(A11>=2014,Y11=1),1,0) -> 0 | Y11: =IF(COUNT(D11:H11)=5,1,0) -> 1
A12: 2013 | B12: 11 | C12: =12*(A12-1960)+B12-1 -> 646 | D12: 11963 | E12: =IF(COUNT(T12:U12)=2,T12-U12,"") -> 0.7896 | F12: =IF(COUNT(flow_components!C12:E12)=3,SUM(flow_components!C12:E12),"") -> 2.5108392 | G12: 90.35198 | H12: 80.68 | I12: 2.7445 | J12: 13.7 | K12: 7.5 | L12: 0 | M12: 0.25 | N12: =(L12+M12)/2 -> 0.125 | O12: =K12-N12 -> 7.375 | P12: =IF(COUNTIFS(rating_events!$B$2:$B$13,C12,rating_events!$D$2:$D$13,"rating_upgrade")>0,1,0) -> 0 | Q12: =IF(COUNTIFS(rating_events!$B$2:$B$13,C12,rating_events!$D$2:$D$13,"rating_downgrade")>0,1,0) -> 0 | R12: =IF(COUNTIFS(rating_events!$B$2:$B$13,C12,rating_events!$D$2:$D$13,"outlook_improvement")>0,1,0) -> 0 | S12: =IF(COUNTIFS(rating_events!$B$2:$B$13,C12,rating_events!$D$2:$D$13,"outlook_deterioration")>0,1,0) -> 0 | T12: 15.9386 | U12: 15.149 | V12: 0 | W12: 0 | X12: =IF(AND(A12>=2014,Y12=1),1,0) -> 0 | Y12: =IF(COUNT(D12:H12)=5,1,0) -> 1
A13: 2013 | B13: 12 | C13: =12*(A13-1960)+B13-1 -> 647 | D13: 12170 | E13: =IF(COUNT(T13:U13)=2,T13-U13,"") -> 1.5118 | F13: =IF(COUNT(flow_components!C13:E13)=3,SUM(flow_components!C13:E13),"") -> -4.8763704 | G13: 92.872318 | H13: 80.035 | I13: 3.0282 | J13: 13.72 | K13: 7.5 | L13: 0 | M13: 0.25 | N13: =(L13+M13)/2 -> 0.125 | O13: =K13-N13 -> 7.375 | P13: =IF(COUNTIFS(rating_events!$B$2:$B$13,C13,rating_events!$D$2:$D$13,"rating_upgrade")>0,1,0) -> 0 | Q13: =IF(COUNTIFS(rating_events!$B$2:$B$13,C13,rating_events!$D$2:$D$13,"rating_downgrade")>0,1,0) -> 0 | R13: =IF(COUNTIFS(rating_events!$B$2:$B$13,C13,rating_events!$D$2:$D$13,"outlook_improvement")>0,1,0) -> 0 | S13: =IF(COUNTIFS(rating_events!$B$2:$B$13,C13,rating_events!$D$2:$D$13,"outlook_deterioration")>0,1,0) -> 0 | T13: 16.9678 | U13: 15.456 | V13: 0 | W13: 0 | X13: =IF(AND(A13>=2014,Y13=1),1,0) -> 0 | Y13: =IF(COUNT(D13:H13)=5,1,0) -> 1
... A165: 2026 | B165: 8 | C165: =12*(A165-1960)+B165-1 -> 799 | D165: 17720 | E165: =IF(COUNT(T165:U165)=2,T165-U165,"") -> 3.5522 | F165: =IF(COUNT(flow_components!C165:E165)=3,SUM(flow_components!C165:E165),"") -> 24.138935 | G165: 124.66819 | H165: 99.428 | I165: 4.75 | J165: 14.92 | K165: 5.75 | L165: 3.5 | M165: 3.75 | N165: =(L165+M165)/2 -> 3.625 | O165: =K165-N165 -> 2.125 | P165: =IF(COUNTIFS(rating_events!$B$2:$B$13,C165,rating_events!$D$2:$D$13,"rating_upgrade")>0,1,0) -> 0 | Q165: =IF(COUNTIFS(rating_events!$B$2:$B$13,C165,rating_events!$D$2:$D$13,"rating_downgrade")>0,1,0) -> 0 | R165: =IF(COUNTIFS(rating_events!$B$2:$B$13,C165,rating_events!$D$2:$D$13,"outlook_improvement")>0,1,0) -> 0 | S165: =IF(COUNTIFS(rating_events!$B$2:$B$13,C165,rating_events!$D$2:$D$13,"outlook_deterioration")>0,1,0) -> 0 | T165: 26.6122 | U165: 23.06 | V165: 1 | W165: 1 | X165: =IF(AND(A165>=2014,Y165=1),1,0) -> 1 | Y165: =IF(COUNT(D165:H165)=5,1,0) -> 1
A166: 2026 | B166: 9 | C166: =12*(A166-1960)+B166-1 -> 800 | D166: 17870 | E166: =IF(COUNT(T166:U166)=2,T166-U166,"") | F166: =IF(COUNT(flow_components!C166:E166)=3,SUM(flow_components!C166:E166),"") -> -12.099099 | G166: 125.18737 | H166: 101.451 | I166: 5.2849 | J166: 16.34 | K166: 5.75 | L166: 3.75 | M166: 4 | N166: =(L166+M166)/2 -> 3.875 | O166: =K166-N166 -> 1.875 | P166: =IF(COUNTIFS(rating_events!$B$2:$B$13,C166,rating_events!$D$2:$D$13,"rating_upgrade")>0,1,0) -> 0 | Q166: =IF(COUNTIFS(rating_events!$B$2:$B$13,C166,rating_events!$D$2:$D$13,"rating_downgrade")>0,1,0) -> 0 | R166: =IF(COUNTIFS(rating_events!$B$2:$B$13,C166,rating_events!$D$2:$D$13,"outlook_improvement")>0,1,0) -> 0 | S166: =IF(COUNTIFS(rating_events!$B$2:$B$13,C166,rating_events!$D$2:$D$13,"outlook_deterioration")>0,1,0) -> 0 | V166: 1 | W166: 1 | X166: =IF(AND(A166>=2014,Y166=1),1,0) -> 0 | Y166: =IF(COUNT(D166:H166)=5,1,0) -> 0

Sheet flow_components
A1: year | B1: month | C1: flow_saham_idrtn | D1: flow_sbn_idrtn | E1: flow_srbi_idrtn | F1: sbn_basis | G1: srbi_basis | H1: source_sheet_row
A2: 2013 | B2: 1 | C2: 5.6954681 | D2: 1.9700842 | E2: 0 | F2: IDGBFNBN daily source series | G2: Pra-SRBI | H2: 69
A3: 2013 | B3: 2 | C3: 11.242296 | D3: 7.1602962 | E3: 0 | F3: IDGBFNBN daily source series | G3: Pra-SRBI | H3: 70
A4: 2013 | B4: 3 | C4: 1.8279823 | D4: -1.2899433 | E4: 0 | F4: IDGBFNBN daily source series | G4: Pra-SRBI | H4: 71
A5: 2013 | B5: 4 | C5: 0.72206704 | D5: 15.740046 | E5: 0 | F5: IDGBFNBN daily source series | G5: Pra-SRBI | H5: 72
A6: 2013 | B6: 5 | C6: -0.35588172 | D6: 3.9500305 | E6: 0 | F6: IDGBFNBN daily source series | G6: Pra-SRBI | H6: 73
A7: 2013 | B7: 6 | C7: -20.132098 | D7: -19.260208 | E7: 0 | F7: IDGBFNBN daily source series | G7: Pra-SRBI | H7: 74
A8: 2013 | B8: 7 | C8: -2.4802534 | D8: 2.8100575 | E8: 0 | F8: IDGBFNBN daily source series | G8: Pra-SRBI | H8: 75
A9: 2013 | B9: 8 | C9: -5.6951952 | D9: -2.1401475 | E9: 0 | F9: IDGBFNBN daily source series | G9: Pra-SRBI | H9: 76
A10: 2013 | B10: 9 | C10: -0.36518129 | D10: 10.129981 | E10: 0 | F10: IDGBFNBN daily source series | G10: Pra-SRBI | H10: 77
A11: 2013 | B11: 10 | C11: -1.9811812 | D11: 23.150264 | E11: 0 | F11: IDGBFNBN daily source series | G11: Pra-SRBI | H11: 78
A12: 2013 | B12: 11 | C12: -3.8590595 | D12: 6.3698987 | E12: 0 | F12: IDGBFNBN daily source series | G12: Pra-SRBI | H12: 79
A13: 2013 | B13: 12 | C13: -5.266339 | D13: 0.38996862 | E13: 0 | F13: IDGBFNBN daily source series | G13: Pra-SRBI | H13: 80
... A166: 2026 | B166: 9 | C166: -10.2435 | D166: -0.344 | E166: -1.511599 | F166: DJPPR month-end nonresident holdings change | G166: Ownership | H166: 233

Sheet rating_events
A1: event_date | B1: mdate | C1: agency | D1: event_type | E1: rating_before | F1: rating_after | G1: outlook_before | H1: outlook_after | I1: source_url
A2: 41396 | B2: 640 | C2: SP | D2: outlook_deterioration | E2: BB+ | F2: BB+ | G2: Positive | H2: Stable | I2: https://www.bi.go.id/en/iru/economic-market-data/Documents/Indonesia%20Sovereign%20Rating%20-%20July%202026.pdf
A3: 42145 | B3: 664 | C3: SP | D3: outlook_improvement | E3: BB+ | F3: BB+ | G3: Stable | H3: Positive | I3: https://www.bi.go.id/en/iru/economic-market-data/Documents/Indonesia%20Sovereign%20Rating%20-%20July%202026.pdf
A4: 42725 | B4: 683 | C4: Fitch | D4: outlook_improvement | E4: BBB- | F4: BBB- | G4: Stable | H4: Positive | I4: https://www.bi.go.id/en/iru/economic-market-data/Documents/Indonesia%20Sovereign%20Rating%20-%20July%202026.pdf
A5: 42774 | B5: 685 | C5: Moodys | D5: outlook_improvement | E5: Baa3 | F5: Baa3 | G5: Stable | H5: Positive | I5: https://www.bi.go.id/en/iru/economic-market-data/Documents/Indonesia%20Sovereign%20Rating%20-%20July%202026.pdf
A6: 42874 | B6: 688 | C6: SP | D6: rating_upgrade | E6: BB+ | F6: BBB- | G6: Positive | H6: Stable | I6: https://www.bi.go.id/en/iru/economic-market-data/Documents/Indonesia%20Sovereign%20Rating%20-%20July%202026.pdf
A7: 43089 | B7: 695 | C7: Fitch | D7: rating_upgrade | E7: BBB- | F7: BBB | G7: Positive | H7: Stable | I7: https://www.bi.go.id/en/iru/economic-market-data/Documents/Indonesia%20Sovereign%20Rating%20-%20July%202026.pdf
A8: 43203 | B8: 699 | C8: Moodys | D8: rating_upgrade | E8: Baa3 | F8: Baa2 | G8: Positive | H8: Stable | I8: https://www.bi.go.id/en/iru/economic-market-data/Documents/Indonesia%20Sovereign%20Rating%20-%20July%202026.pdf
A9: 43616 | B9: 712 | C9: SP | D9: rating_upgrade | E9: BBB- | F9: BBB | G9: Stable | H9: Stable | I9: https://www.bi.go.id/en/iru/economic-market-data/Documents/Indonesia%20Sovereign%20Rating%20-%20July%202026.pdf
A10: 43938 | B10: 723 | C10: SP | D10: outlook_deterioration | E10: BBB | F10: BBB | G10: Stable | H10: Negative | I10: https://www.bi.go.id/en/iru/economic-market-data/Documents/Indonesia%20Sovereign%20Rating%20-%20July%202026.pdf
A11: 44678 | B11: 747 | C11: SP | D11: outlook_improvement | E11: BBB | F11: BBB | G11: Negative | H11: Stable | I11: https://www.bi.go.id/en/iru/economic-market-data/Documents/Indonesia%20Sovereign%20Rating%20-%20July%202026.pdf
A12: 46058 | B12: 793 | C12: Moodys | D12: outlook_deterioration | E12: Baa2 | F12: Baa2 | G12: Stable | H12: Negative | I12: https://www.bi.go.id/en/iru/economic-market-data/Documents/Indonesia%20Sovereign%20Rating%20-%20July%202026.pdf
A13: 46085 | B13: 794 | C13: Fitch | D13: outlook_deterioration | E13: BBB | F13: BBB | G13: Stable | H13: Negative | I13: https://www.bi.go.id/en/iru/economic-market-data/Documents/Indonesia%20Sovereign%20Rating%20-%20July%202026.pdf

Sheet sources
A1: variable | B1: definition | C1: unit | D1: aggregation | E1: source | F1: reference | G1: coverage | H1: accessed_on | I1: notes
A2: year; month; mdate | B2: Tahun, bulan dan indeks waktu bulanan Stata | C2: year; month; Stata %tm | D2: Satu observasi per bulan | E2: Calendar / derived | F2: Stata monthly date: mdate=12*(year-1960)+month-1 | G2: 2013-01 to 2026-09 | H2: 2026-10-30 | I2: Stata: format mdate %tm; tsset mdate. Tahun dan bulan berupa angka.
A3: usdidr | B3: Nilai tukar pasar USD/IDR; bukan JISDOR | C3: IDR per USD | D3: Nilai terakhir dalam bulan | E3: Bloomberg, file pengguna | F3: https://chatgpt.com/library?file_id=libfile_eda684a00c348191811a01c1828431f5&account_id=personal | G3: 2013-01 to 2026-09 | H3: 2026-10-30 | I3: Asset Market Updater - Stasis 21 oktober 2026 (1).xlsx | Currencies!A8:A9789 dan M8:M9789 | IDR REGN Curncy, PX_Last. JISDOR tidak berhasil diunduh: filter situs BI menolak akses. Tidak disambung dengan JISDOR.
A4: dxy | B4: US Dollar Index | C4: index | D4: Nilai terakhir dalam bulan | E4: Bloomberg, file pengguna | F4: https://chatgpt.com/library?file_id=libfile_eda684a00c348191811a01c1828431f5&account_id=personal | G4: 2013-01 to 2026-09 | H4: 2026-10-30 | I4: Asset Market Updater - Stasis 21 oktober 2026 (1).xlsx | Currencies!A8:A9789 dan G8:G9789 | DXY Curncy, PX_Last. Hari nonperdagangan dalam file dapat merupakan carry-forward.
A5: ust10y_pct | B5: Yield US Treasury tenor 10 tahun | C5: percent | D5: Nilai terakhir dalam bulan | E5: Bloomberg, file pengguna | F5: https://chatgpt.com/library?file_id=libfile_eda684a00c348191811a01c1828431f5&account_id=personal | G5: 2013-01 to 2026-09 | H5: 2026-10-30 | I5: Asset Market Updater - Stasis 21 oktober 2026 (1).xlsx | US Govt Bonds!A8:A9789 dan J8:J9789 | USGG10YR Index, PX_Last. Disimpan sebagai angka persen, contoh 4.25.
A6: net_flows_idrtn | B6: Gabungan arus asing saham, SBN dan SRBI | C6: IDR trillion | D6: Jumlah tiga komponen bulanan | E6: File flows pengguna | F6: https://chatgpt.com/library?file_id=libfile_4f379503ed0c8191894cbcc3280ca4d3&account_id=personal | G6: 2013-01 to 2026-09 | H6: 2026-10-30 | I6: Grand_Capital_Flows_ACUAN (6).xlsx | Grand Flows: blok bulanan historis, baris dicatat di flow_components. Saham adalah transaksi neto. SBN/SRBI dapat berupa perubahan kepemilikan; agregat merupakan proksi flows ketiga pasar, bukan seluruh financial account. Positif = inflow neto; negatif = outflow neto. Yield Indonesia tidak dimasukkan.
A7: flow_saham_idrtn | B7: Net pembelian asing pasar saham | C7: IDR trillion | D7: Jumlah observasi harian dalam bulan | E7: Bloomberg/BEI di file pengguna | F7: https://chatgpt.com/library?file_id=libfile_4f379503ed0c8191894cbcc3280ca4d3&account_id=personal | G7: 2013-01 to 2026-09 | H7: 2026-10-30 | I7: Stocks Daily kolom A dan F; direkonsiliasi terhadap Grand Flows. Riwayat sebelum data BEI terbaru mengikuti seri acuan pengguna JASXNET$.
A8: flow_sbn_idrtn | B8: Arus SBN seri pengguna / perubahan kepemilikan nonresiden | C8: IDR trillion | D8: 2013-2025: jumlah seri harian; 2026: perubahan posisi akhir bulan | E8: Seri acuan pengguna / DJPPR | F8: https://chatgpt.com/library?file_id=libfile_4f379503ed0c8191894cbcc3280ca4d3&account_id=personal | G8: 2013-01 to 2026-09 | H8: 2026-10-30 | I8: SBN Daily kolom A dan G; bulanan 2026 mengikuti kontrol posisi DJPPR di file sumber. Perubahan posisi dapat mencakup jatuh tempo, bukan transaksi pasar sekunder murni.
A9: flow_srbi_idrtn | B9: Perubahan posisi SRBI nonresiden | C9: IDR trillion | D9: Perubahan posisi akhir bulan | E9: Bank Indonesia melalui file pengguna | F9: https://chatgpt.com/library?file_id=libfile_4f379503ed0c8191894cbcc3280ca4d3&account_id=personal | G9: 2023-09 to 2026-09 | H9: 2026-10-30 | I9: SRBI Monthly kolom O (flow terpilih), basis Ownership untuk seluruh bulan yang dipakai. Sebelum September 2023 = 0 karena instrumen belum ada. Data kosong setelah peluncuran tidak diganti nol.
A10: exports_usdbn | B10: Ekspor barang Indonesia, FOB | C10: USD billion | D10: Total transaksi selama bulan | E10: Badan Pusat Statistik | F10: https://www.bps.go.id/id/statistics-table/2/MTk2IzI%3D/nilai-ekspor.html | G10: 2013-01 to 2026-08 | H10: 2026-10-30 | I10: Tabel dinamis 196, domain 0000, Indonesia 9999, turunan bulanan 1-12. Diambil per tahun 2013-2026. Angka asli juta USD dibagi 1000. September 2026 belum tersedia pada sumber saat akses.
A11: imports_usdbn | B11: Impor barang Indonesia, CIF | C11: USD billion | D11: Total transaksi selama bulan | E11: Badan Pusat Statistik | F11: https://www.bps.go.id/id/statistics-table/2/NDk3IzI%3D/nilai-impor.html | G11: 2015-01 to 2026-08 | H11: 2026-10-30 | I11: Tabel dinamis 497, domain 0000, Indonesia 9999. Angka asli juta USD dibagi 1000. Tabel ini tidak memiliki 2013-2014.
A12: imports_usdbn | B12: Impor barang Indonesia, CIF; pelengkap tahun awal | C12: USD billion | D12: Total transaksi selama bulan | E12: IMF, International Trade in Goods | F12: https://api.imf.org/external/sdmx/2.1/data/ITG/IDN.MG..M?startPeriod=2013-01&endPeriod=2015-12 | G12: 2013-01 to 2014-12 | H12: 2026-10-30 | I12: Dipilih COUNTRY=IDN, INDICATOR=MG, TYPE_OF_TRANSFORMATION=CIF_USD, FREQUENCY=M. OBS_VALUE dalam USD dibagi 1e9. Sumber lebih bulat daripada tabel BPS. Overlap 2015 berbeda kurang dari USD1 juta per bulan; tidak digunakan mengganti BPS 2015 dan sesudahnya.
... A30: database_vintage | B30: Tanggal informasi dan perlakuan revisi | C30: date | D30: Snapshot sumber yang tersedia saat akses | E30: All sources | F30: Sources listed above | G30: As of 2026-10-30 | H30: 2026-10-30 | I30: Data merupakan latest available vintage, bukan arsip vintage real-time. Untuk backtest, gunakan keterlambatan rilis dan perlakuan revisi yang tepat. Oktober 2026 dikeluarkan karena belum merupakan bulan penuh dan file pasar berhenti 21 Oktober 2026.
